combs/__init__.py
combs/combinations.py
PyCombs-1.0.0.dist-info/LICENSE
PyCombs-1.0.0.dist-info/METADATA
PyCombs-1.0.0.dist-info/WHEEL
PyCombs-1.0.0.dist-info/top_level.txt
PyCombs-1.0.0.dist-info/RECORD
