Metadata-Version: 2.1
Name: PyCombs
Version: 1.0.0
Summary: A package that generates all possible combinations in a given set as a list
Home-page: https://github.com/yanismnsr/PyCombinations
Author: Yanis MANSOUR
Author-email: mansouryanis6@gmail.com
License: UNKNOWN
Project-URL: Bug Tracker, https://github.com/yanismnsr/PyCombinations/issues
Platform: UNKNOWN
Classifier: Programming Language :: Python :: 3
Classifier: License :: OSI Approved :: GNU General Public License v3 (GPLv3)
Classifier: Operating System :: OS Independent
Requires-Python: >=3.0
License-File: LICENSE
